vita/LICENSE
vita/__init__.py
vita/version.py
vita/vita.pyd
vita/constants/__init__.py
vita-0.0.5.dist-info/licenses/LICENSE
vita-0.0.5.dist-info/METADATA
vita-0.0.5.dist-info/WHEEL
vita-0.0.5.dist-info/top_level.txt
vita-0.0.5.dist-info/RECORD
