Metadata-Version: 2.4
Name: vita
Version: 0.0.5
Summary: Python bindings for the Vital synthesizer
Home-page: https://github.com/DBraun/Vita
Author: David Braun
Author-email: braun@ccrma.stanford.edu
Project-URL: Documentation, https://dirt.design/Vita
Project-URL: Source, https://github.com/DBraun/Vita
Keywords: audio music sound synthesizer
Classifier: Development Status :: 3 - Alpha
Classifier: Intended Audience :: Developers
Classifier: License :: OSI Approved :: GNU General Public License v3 (GPLv3)
Classifier: Operating System :: MacOS
Classifier: Operating System :: Microsoft :: Windows
Classifier: Operating System :: POSIX :: Linux
Classifier: Programming Language :: C++
Classifier: Programming Language :: Python
Classifier: Topic :: Multimedia :: Sound/Audio
Classifier: Programming Language :: Python :: 3.9
Classifier: Programming Language :: Python :: 3.10
Classifier: Programming Language :: Python :: 3.11
Classifier: Programming Language :: Python :: 3.12
Classifier: Programming Language :: Python :: 3.13
Requires-Python: >=3.9
License-File: LICENSE
Dynamic: author
Dynamic: author-email
Dynamic: classifier
Dynamic: description
Dynamic: description-content-type
Dynamic: home-page
Dynamic: keywords
Dynamic: license-file
Dynamic: project-url
Dynamic: requires-python
Dynamic: summary
